reslot.py
reslot-0.10.dist-info/licenses/LICENSE
reslot-0.10.dist-info/METADATA
reslot-0.10.dist-info/WHEEL
reslot-0.10.dist-info/top_level.txt
reslot-0.10.dist-info/RECORD
