Metadata-Version: 2.4
Name: reslot
Version: 0.10
Summary: Class decorator to enable @cached_property on classes with __slots__
Author-email: Zachary Spector <public@zacharyspector.com>
License-Expression: MIT
Project-URL: Homepage, https://codeberg.org/clayote/reslot
Project-URL: Bug tracker, https://codeberg.org/clayote/reslot/issues
Classifier: Programming Language :: Python :: 3
Classifier: Operating System :: OS Independent
Classifier: Topic :: Software Development :: Libraries
Classifier: Development Status :: 3 - Alpha
Requires-Python: ~=3.8
License-File: LICENSE
Dynamic: license-file
